README.md
setup.py
laneDetectionCV/__init__.py
laneDetectionCV/inference.py
laneDetectionCV.egg-info/PKG-INFO
laneDetectionCV.egg-info/SOURCES.txt
laneDetectionCV.egg-info/dependency_links.txt
laneDetectionCV.egg-info/top_level.txt
laneDetectionCV/nets/__init__.py
laneDetectionCV/nets/aspp.py
laneDetectionCV/nets/decoder.py
laneDetectionCV/nets/deeplab.py
laneDetectionCV/nets/resnet.py
laneDetectionCV/utils/__init__.py
laneDetectionCV/utils/data.py