Metadata-Version: 1.2
Name: laneDetectionCV
Version: 0.0.11
Summary: lane detection package
Home-page: https://github.com/Krascal/laneDetection/tree/master/laneDetection
Author: krascal
Author-email: luanxuke@126.com
License: UNKNOWN
Platform: UNKNOWN
Classifier: Programming Language :: Python :: 3
Classifier: License :: OSI Approved :: MIT License
Classifier: Operating System :: OS Independent
Requires-Python: >=3
